hocho/__init__.py
hocho/cleaning.py
hocho/normalization.py
hocho/stopwords.py
hocho/tokenizer/__init__.py
hocho/tokenizer/tokenizer.py
hocho/tokenizer/impl/__init__.py
hocho/tokenizer/impl/mecab_tokenizer.py
ho_cho-0.0.3.dist-info/METADATA
ho_cho-0.0.3.dist-info/WHEEL
ho_cho-0.0.3.dist-info/top_level.txt
ho_cho-0.0.3.dist-info/RECORD
