Metadata-Version: 2.1
Name: ho-cho
Version: 0.0.3
Summary: ho-cho is japanese language processing package.
Home-page: https://github.com/gtaiyou24/ho-cho
Author: taiyo tamura
Author-email: gtaiyou24@gmail.com
Requires-Dist: beautifulsoup4 (==4.11.1)
Requires-Dist: gensim (==4.3.0)
Requires-Dist: mecab (==0.996.3)
Requires-Dist: nltk (==3.8)
Requires-Dist: pytest (==7.1.3)
